<?xml version="1.0"?>
<GraphicalMotorPrimitive xmlns:xsi="http://www.w3.org/2001/XMLSchema-instance" xmlns:xsd="http://www.w3.org/2001/XMLSchema">
  <entries />
  <name>GoalAnimate</name>
  <gain>1</gain>
  <gainMin>-1</gainMin>
  <gainMax>60</gainMax>
  <GraphicalBlock>
    <EntrySinus>
      <entries />
      <name>EntrySinus</name>
      <gain>3</gain>
      <gainMin>-1</gainMin>
      <gainMax>60</gainMax>
      <period>2</period>
      <shift>0</shift>
      <smooth_update>true</smooth_update>
    </EntrySinus>
    <Position>
      <X>43.156666666666666</X>
      <Y>235</Y>
    </Position>
  </GraphicalBlock>
  <GraphicalBlock>
    <BlockServo>
      <entries>
        <BlockPredecessor>
          <name>EntrySinus</name>
          <output_idx>0</output_idx>
          <condition />
          <fire />
        </BlockPredecessor>
      </entries>
      <name>Bassin Lat</name>
      <gain>1</gain>
      <gainMin>-1</gainMin>
      <gainMax>60</gainMax>
      <UseWrongMX28Conversion>false</UseWrongMX28Conversion>
      <servo_name>Bassin Lat</servo_name>
      <unit>1</unit>
      <relative>1</relative>
    </BlockServo>
    <Position>
      <X>334</X>
      <Y>137</Y>
    </Position>
  </GraphicalBlock>
  <GraphicalBlockLink>
    <output_value>0</output_value>
    <Condition />
    <Fire />
    <SourceIndex>0</SourceIndex>
    <TargetIndex>0</TargetIndex>
    <SourceName>EntrySinus</SourceName>
    <TargetName>Bassin Lat</TargetName>
  </GraphicalBlockLink>
  <GraphicalBlock>
    <Constant>
      <entries />
      <name>Constant</name>
      <gain>1</gain>
      <gainMin>-1</gainMin>
      <gainMax>60</gainMax>
      <constants>
        <float>45</float>
      </constants>
    </Constant>
    <Position>
      <X>77</X>
      <Y>44</Y>
    </Position>
  </GraphicalBlock>
  <GraphicalBlock>
    <BlockServo>
      <entries>
        <BlockPredecessor>
          <name>Constant</name>
          <output_idx>0</output_idx>
          <condition />
          <fire />
        </BlockPredecessor>
      </entries>
      <name>Coude G1</name>
      <gain>1</gain>
      <gainMin>-1</gainMin>
      <gainMax>60</gainMax>
      <UseWrongMX28Conversion>false</UseWrongMX28Conversion>
      <servo_name>Coude G</servo_name>
      <unit>1</unit>
      <relative>1</relative>
    </BlockServo>
    <Position>
      <X>304</X>
      <Y>5</Y>
    </Position>
  </GraphicalBlock>
  <GraphicalBlockLink>
    <output_value>0</output_value>
    <Condition />
    <Fire />
    <SourceIndex>0</SourceIndex>
    <TargetIndex>0</TargetIndex>
    <SourceName>Constant</SourceName>
    <TargetName>Coude G1</TargetName>
  </GraphicalBlockLink>
  <GraphicalBlock>
    <BlockGain>
      <entries />
      <name>BlockGain</name>
      <gain>1</gain>
      <gainMin>-1</gainMin>
      <gainMax>60</gainMax>
      <gains />
    </BlockGain>
    <Position>
      <X>142</X>
      <Y>-164</Y>
    </Position>
  </GraphicalBlock>
  <GraphicalBlock>
    <BlockGain>
      <entries>
        <BlockPredecessor>
          <name>Constant</name>
          <output_idx>0</output_idx>
          <condition />
          <fire />
        </BlockPredecessor>
      </entries>
      <name>BlockGain1</name>
      <gain>1</gain>
      <gainMin>-1</gainMin>
      <gainMax>60</gainMax>
      <gains>
        <float>-1</float>
      </gains>
    </BlockGain>
    <Position>
      <X>212</X>
      <Y>65</Y>
    </Position>
  </GraphicalBlock>
  <GraphicalBlockLink>
    <output_value>0</output_value>
    <Condition />
    <Fire />
    <SourceIndex>0</SourceIndex>
    <TargetIndex>0</TargetIndex>
    <SourceName>Constant</SourceName>
    <TargetName>BlockGain1</TargetName>
  </GraphicalBlockLink>
  <GraphicalBlock>
    <BlockServo>
      <entries>
        <BlockPredecessor>
          <name>BlockGain1</name>
          <output_idx>0</output_idx>
          <condition />
          <fire />
        </BlockPredecessor>
      </entries>
      <name>Coude D1</name>
      <gain>1</gain>
      <gainMin>-1</gainMin>
      <gainMax>60</gainMax>
      <UseWrongMX28Conversion>false</UseWrongMX28Conversion>
      <servo_name>Coude D</servo_name>
      <unit>1</unit>
      <relative>1</relative>
    </BlockServo>
    <Position>
      <X>304</X>
      <Y>65</Y>
    </Position>
  </GraphicalBlock>
  <GraphicalBlockLink>
    <output_value>0</output_value>
    <Condition />
    <Fire />
    <SourceIndex>0</SourceIndex>
    <TargetIndex>0</TargetIndex>
    <SourceName>BlockGain1</SourceName>
    <TargetName>Coude D1</TargetName>
  </GraphicalBlockLink>
  <GraphicalBlock>
    <BlockServo>
      <entries>
        <BlockPredecessor>
          <name>EntrySinus</name>
          <output_idx>0</output_idx>
          <condition />
          <fire />
        </BlockPredecessor>
      </entries>
      <name>Epaule G Lat</name>
      <gain>1</gain>
      <gainMin>-1</gainMin>
      <gainMax>60</gainMax>
      <UseWrongMX28Conversion>false</UseWrongMX28Conversion>
      <servo_name>Epaule G Lat</servo_name>
      <unit>1</unit>
      <relative>1</relative>
    </BlockServo>
    <Position>
      <X>334</X>
      <Y>188</Y>
    </Position>
  </GraphicalBlock>
  <GraphicalBlockLink>
    <output_value>0</output_value>
    <Condition />
    <Fire />
    <SourceIndex>0</SourceIndex>
    <TargetIndex>0</TargetIndex>
    <SourceName>EntrySinus</SourceName>
    <TargetName>Epaule G Lat</TargetName>
  </GraphicalBlockLink>
  <GraphicalBlock>
    <BlockServo>
      <entries>
        <BlockPredecessor>
          <name>EntrySinus</name>
          <output_idx>0</output_idx>
          <condition />
          <fire />
        </BlockPredecessor>
      </entries>
      <name>Epaule D Lat</name>
      <gain>1</gain>
      <gainMin>-1</gainMin>
      <gainMax>60</gainMax>
      <UseWrongMX28Conversion>false</UseWrongMX28Conversion>
      <servo_name>Epaule D Lat</servo_name>
      <unit>1</unit>
      <relative>1</relative>
    </BlockServo>
    <Position>
      <X>334</X>
      <Y>235</Y>
    </Position>
  </GraphicalBlock>
  <GraphicalBlockLink>
    <output_value>0</output_value>
    <Condition />
    <Fire />
    <SourceIndex>0</SourceIndex>
    <TargetIndex>0</TargetIndex>
    <SourceName>EntrySinus</SourceName>
    <TargetName>Epaule D Lat</TargetName>
  </GraphicalBlockLink>
  <GraphicalBlock>
    <BlockServo>
      <entries>
        <BlockPredecessor>
          <name>BlockGain2</name>
          <output_idx>0</output_idx>
          <condition />
          <fire />
        </BlockPredecessor>
      </entries>
      <name>Genou G</name>
      <gain>1</gain>
      <gainMin>-1</gainMin>
      <gainMax>60</gainMax>
      <UseWrongMX28Conversion>false</UseWrongMX28Conversion>
      <servo_name>Genou G</servo_name>
      <unit>1</unit>
      <relative>1</relative>
    </BlockServo>
    <Position>
      <X>334</X>
      <Y>295</Y>
    </Position>
  </GraphicalBlock>
  <GraphicalBlock>
    <BlockServo>
      <entries>
        <BlockPredecessor>
          <name>BlockGain2</name>
          <output_idx>0</output_idx>
          <condition />
          <fire />
        </BlockPredecessor>
      </entries>
      <name>Genou D</name>
      <gain>1</gain>
      <gainMin>-1</gainMin>
      <gainMax>60</gainMax>
      <UseWrongMX28Conversion>false</UseWrongMX28Conversion>
      <servo_name>Genou D</servo_name>
      <unit>1</unit>
      <relative>1</relative>
    </BlockServo>
    <Position>
      <X>334</X>
      <Y>342</Y>
    </Position>
  </GraphicalBlock>
  <GraphicalBlock>
    <BlockGain>
      <entries>
        <BlockPredecessor>
          <name>EntrySinus</name>
          <output_idx>0</output_idx>
          <condition />
          <fire />
        </BlockPredecessor>
      </entries>
      <name>BlockGain2</name>
      <gain>1</gain>
      <gainMin>-1</gainMin>
      <gainMax>60</gainMax>
      <gains>
        <float>-1</float>
      </gains>
    </BlockGain>
    <Position>
      <X>234</X>
      <Y>311</Y>
    </Position>
  </GraphicalBlock>
  <GraphicalBlockLink>
    <output_value>0</output_value>
    <Condition />
    <Fire />
    <SourceIndex>0</SourceIndex>
    <TargetIndex>0</TargetIndex>
    <SourceName>EntrySinus</SourceName>
    <TargetName>BlockGain2</TargetName>
  </GraphicalBlockLink>
  <GraphicalBlockLink>
    <output_value>0</output_value>
    <Condition />
    <Fire />
    <SourceIndex>0</SourceIndex>
    <TargetIndex>0</TargetIndex>
    <SourceName>BlockGain2</SourceName>
    <TargetName>Genou G</TargetName>
  </GraphicalBlockLink>
  <GraphicalBlockLink>
    <output_value>0</output_value>
    <Condition />
    <Fire />
    <SourceIndex>0</SourceIndex>
    <TargetIndex>0</TargetIndex>
    <SourceName>BlockGain2</SourceName>
    <TargetName>Genou D</TargetName>
  </GraphicalBlockLink>
  <GraphicalBlock>
    <BlockServo>
      <entries>
        <BlockPredecessor>
          <name>EntrySinus</name>
          <output_idx>0</output_idx>
          <condition />
          <fire />
        </BlockPredecessor>
      </entries>
      <name>Coude G</name>
      <gain>1</gain>
      <gainMin>-1</gainMin>
      <gainMax>60</gainMax>
      <UseWrongMX28Conversion>false</UseWrongMX28Conversion>
      <servo_name>Coude G</servo_name>
      <unit>1</unit>
      <relative>1</relative>
    </BlockServo>
    <Position>
      <X>334</X>
      <Y>402</Y>
    </Position>
  </GraphicalBlock>
  <GraphicalBlock>
    <BlockServo>
      <entries>
        <BlockPredecessor>
          <name>EntrySinus</name>
          <output_idx>0</output_idx>
          <condition />
          <fire />
        </BlockPredecessor>
      </entries>
      <name>Coude D</name>
      <gain>1</gain>
      <gainMin>-1</gainMin>
      <gainMax>60</gainMax>
      <UseWrongMX28Conversion>false</UseWrongMX28Conversion>
      <servo_name>Coude D</servo_name>
      <unit>1</unit>
      <relative>1</relative>
    </BlockServo>
    <Position>
      <X>334</X>
      <Y>461</Y>
    </Position>
  </GraphicalBlock>
  <GraphicalBlockLink>
    <output_value>0</output_value>
    <Condition />
    <Fire />
    <SourceIndex>0</SourceIndex>
    <TargetIndex>0</TargetIndex>
    <SourceName>EntrySinus</SourceName>
    <TargetName>Coude G</TargetName>
  </GraphicalBlockLink>
  <GraphicalBlockLink>
    <output_value>0</output_value>
    <Condition />
    <Fire />
    <SourceIndex>0</SourceIndex>
    <TargetIndex>0</TargetIndex>
    <SourceName>EntrySinus</SourceName>
    <TargetName>Coude D</TargetName>
  </GraphicalBlockLink>
  <hsize>500</hsize>
  <vsize>500</vsize>
  <SchemaComments />
  <Frequency>100</Frequency>
  <SmoothStart>1000</SmoothStart>
  <SmoothStop>1000</SmoothStop>
  <Duration>0</Duration>
</GraphicalMotorPrimitive>