<?xml version="1.0"?>
<GraphicalMotorPrimitive xmlns:xsi="http://www.w3.org/2001/XMLSchema-instance" xmlns:xsd="http://www.w3.org/2001/XMLSchema">
  <entries />
  <name>NewMove</name>
  <gain>1</gain>
  <GraphicalBlock>
    <AccelerometerBlock>
      <entries />
      <name>AccelerometerBlock</name>
      <gain>1</gain>
    </AccelerometerBlock>
    <Position>
      <X>90</X>
      <Y>189</Y>
    </Position>
  </GraphicalBlock>
  <GraphicalBlock>
    <Spline>
      <entries>
        <BlockPredecessor>
          <name>BlockDigitalLevel</name>
          <output_idx>0</output_idx>
        </BlockPredecessor>
      </entries>
      <name>Spline</name>
      <gain>1</gain>
      <sequences>
        <SplineSequence>
          <Points>
            <SplinePoint>
              <left_tangent>0</left_tangent>
              <right_tangent>0</right_tangent>
              <x>0</x>
              <y>80</y>
            </SplinePoint>
            <SplinePoint>
              <left_tangent>0</left_tangent>
              <right_tangent>0</right_tangent>
              <x>1</x>
              <y>0</y>
            </SplinePoint>
          </Points>
          <name>Genou G</name>
          <cyclic>0</cyclic>
          <type>0</type>
          <bounded>1</bounded>
          <CyclicBool>false</CyclicBool>
          <BoundedBool>true</BoundedBool>
        </SplineSequence>
        <SplineSequence>
          <Points>
            <SplinePoint>
              <left_tangent>0</left_tangent>
              <right_tangent>0</right_tangent>
              <x>0</x>
              <y>-80</y>
            </SplinePoint>
            <SplinePoint>
              <left_tangent>0</left_tangent>
              <right_tangent>0</right_tangent>
              <x>1</x>
              <y>0</y>
            </SplinePoint>
          </Points>
          <name>Genou D</name>
          <cyclic>0</cyclic>
          <type>0</type>
          <bounded>1</bounded>
          <CyclicBool>false</CyclicBool>
          <BoundedBool>true</BoundedBool>
        </SplineSequence>
      </sequences>
      <shift>0</shift>
      <speed_factor>1</speed_factor>
      <entrytype>1</entrytype>
      <autostart>1</autostart>
    </Spline>
    <Position>
      <X>343</X>
      <Y>198</Y>
    </Position>
  </GraphicalBlock>
  <GraphicalBlock>
    <BlockServo>
      <entries>
        <BlockPredecessor>
          <name>Spline</name>
          <output_idx>0</output_idx>
        </BlockPredecessor>
      </entries>
      <name>Genou G</name>
      <gain>1</gain>
      <servo_name>Genou G</servo_name>
      <unit>1</unit>
      <relative>1</relative>
    </BlockServo>
    <Position>
      <X>477</X>
      <Y>176</Y>
    </Position>
  </GraphicalBlock>
  <GraphicalBlockLink>
    <output_value>-30</output_value>
    <SourceIndex>0</SourceIndex>
    <TargetIndex>0</TargetIndex>
    <SourceName>Spline</SourceName>
    <TargetName>Genou G</TargetName>
  </GraphicalBlockLink>
  <GraphicalBlock>
    <BlockServo>
      <entries>
        <BlockPredecessor>
          <name>Spline</name>
          <output_idx>1</output_idx>
        </BlockPredecessor>
      </entries>
      <name>Genou D</name>
      <gain>1</gain>
      <servo_name>Genou D</servo_name>
      <unit>1</unit>
      <relative>1</relative>
    </BlockServo>
    <Position>
      <X>477</X>
      <Y>216</Y>
    </Position>
  </GraphicalBlock>
  <GraphicalBlockLink>
    <output_value>30</output_value>
    <SourceIndex>1</SourceIndex>
    <TargetIndex>0</TargetIndex>
    <SourceName>Spline</SourceName>
    <TargetName>Genou D</TargetName>
  </GraphicalBlockLink>
  <GraphicalBlock>
    <BlockDigitalLevel>
      <entries>
        <BlockPredecessor>
          <name>BlockMobileAverage</name>
          <output_idx>0</output_idx>
        </BlockPredecessor>
      </entries>
      <name>BlockDigitalLevel</name>
      <gain>1</gain>
      <min_value>
        <float>-0.05</float>
      </min_value>
      <max_value>
        <float>0.1</float>
      </max_value>
      <output_low>0</output_low>
      <output_medium>0</output_medium>
      <output_high>1</output_high>
      <hysteresis>true</hysteresis>
    </BlockDigitalLevel>
    <Position>
      <X>221</X>
      <Y>201</Y>
    </Position>
  </GraphicalBlock>
  <GraphicalBlockLink>
    <output_value>1</output_value>
    <SourceIndex>0</SourceIndex>
    <TargetIndex>0</TargetIndex>
    <SourceName>BlockDigitalLevel</SourceName>
    <TargetName>Spline</TargetName>
  </GraphicalBlockLink>
  <GraphicalBlock>
    <BlockMobileAverage>
      <entries>
        <BlockPredecessor>
          <name>AccelerometerBlock</name>
          <output_idx>3</output_idx>
        </BlockPredecessor>
      </entries>
      <name>BlockMobileAverage</name>
      <gain>1</gain>
      <discount_factor>0.9</discount_factor>
    </BlockMobileAverage>
    <Position>
      <X>153</X>
      <Y>214</Y>
    </Position>
  </GraphicalBlock>
  <GraphicalBlockLink>
    <output_value>0.23600000143051148</output_value>
    <SourceIndex>3</SourceIndex>
    <TargetIndex>0</TargetIndex>
    <SourceName>AccelerometerBlock</SourceName>
    <TargetName>BlockMobileAverage</TargetName>
  </GraphicalBlockLink>
  <GraphicalBlockLink>
    <output_value>0.18000000715255737</output_value>
    <SourceIndex>0</SourceIndex>
    <TargetIndex>0</TargetIndex>
    <SourceName>BlockMobileAverage</SourceName>
    <TargetName>BlockDigitalLevel</TargetName>
  </GraphicalBlockLink>
  <hsize>500</hsize>
  <vsize>500</vsize>
  <filename>NewMove.graphics.xml</filename>
  <Frequency>100</Frequency>
  <SmoothStart>0</SmoothStart>
  <SmoothStop>0</SmoothStop>
  <Duration>0</Duration>
</GraphicalMotorPrimitive>